[
  {
    "home": [
      {
        "league": "西丁",
        "home": "特雷唐吉",
        "away": "艾積多",
        "date": "20-03-09",
        "hfs": "2",
        "afs": "0",
        "hhs": "0",
        "ahs": "0"
      },
      {
        "league": "西丁",
        "home": "1特雷唐吉",
        "away": "波庫納競",
        "date": "20-02-28",
        "hfs": "3",
        "afs": "0",
        "hhs": "1",
        "ahs": "0"
      },
      {
        "league": "西丁",
        "home": "特雷唐吉",
        "away": "拉曼恰競",
        "date": "20-02-17",
        "hfs": "1",
        "afs": "1",
        "hhs": "0",
        "ahs": "0"
      },
      {
        "league": "西丁",
        "home": "特雷唐吉",
        "away": "艾美利亞",
        "date": "19-12-22",
        "hfs": "1",
        "afs": "1",
        "hhs": "0",
        "ahs": "0"
      },
      {
        "league": "西丁",
        "home": "特雷唐吉",
        "away": "CD洛加",
        "date": "19-11-18",
        "hfs": "4",
        "afs": "2",
        "hhs": "2",
        "ahs": "1"
      },
      {
        "league": "西丁",
        "home": "特雷唐吉",
        "away": "CF安提",
        "date": "19-11-04",
        "hfs": "0",
        "afs": "2",
        "hhs": "0",
        "ahs": "2"
      },
      {
        "league": "西丁",
        "home": "特雷唐吉",
        "away": "波利艾美",
        "date": "19-10-21",
        "hfs": "4",
        "afs": "0",
        "hhs": "0",
        "ahs": "0"
      },
      {
        "league": "西丁",
        "home": "1特雷唐吉",
        "away": "馬拉加B1",
        "date": "19-09-23",
        "hfs": "2",
        "afs": "0",
        "hhs": "1",
        "ahs": "0"
      },
      {
        "league": "西丁",
        "home": "特雷唐吉",
        "away": "貝萊斯",
        "date": "19-09-09",
        "hfs": "5",
        "afs": "2",
        "hhs": "0",
        "ahs": "0"
      },
      {
        "league": "西丁",
        "home": "特雷唐吉",
        "away": "CD休伊",
        "date": "19-05-13",
        "hfs": "2",
        "afs": "3",
        "hhs": "0",
        "ahs": "0"
      }
    ],
    "away": [
      {
        "league": "球會友誼",
        "home": "桑羅奎萊",
        "away": "維爾瓦 ",
        "date": "20-09-27",
        "hfs": "1",
        "afs": "0",
        "hhs": "0",
        "ahs": "0"
      },
      {
        "league": "西丙",
        "home": "林恩斯 ",
        "away": "維爾瓦 ",
        "date": "20-03-01",
        "hfs": "1",
        "afs": "0",
        "hhs": "0",
        "ahs": "0"
      },
      {
        "league": "西丙",
        "home": "当贝尼托",
        "away": "維爾瓦 ",
        "date": "20-02-16",
        "hfs": "2",
        "afs": "1",
        "hhs": "1",
        "ahs": "1"
      },
      {
        "league": "西丙",
        "home": "UCAM",
        "away": "維爾瓦 ",
        "date": "20-02-02",
        "hfs": "1",
        "afs": "0",
        "hhs": "0",
        "ahs": "0"
      },
      {
        "league": "西丙",
        "home": "2塔拉維亞",
        "away": "維爾瓦 ",
        "date": "20-01-19",
        "hfs": "0",
        "afs": "1",
        "hhs": "0",
        "ahs": "0"
      },
      {
        "league": "西丙",
        "home": "艾基史拉",
        "away": "維爾瓦 ",
        "date": "19-12-22",
        "hfs": "0",
        "afs": "0",
        "hhs": "0",
        "ahs": "0"
      },
      {
        "league": "西盃",
        "home": "靴格拉斯",
        "away": "維爾瓦 ",
        "date": "19-12-18",
        "hfs": "0",
        "afs": "1",
        "hhs": "0",
        "ahs": "1"
      },
      {
        "league": "西丙",
        "home": "西維爾體",
        "away": "維爾瓦 ",
        "date": "19-12-07",
        "hfs": "1",
        "afs": "3",
        "hhs": "1",
        "ahs": "3"
      },
      {
        "league": "西丙",
        "home": "耶克拉諾",
        "away": "維爾瓦 ",
        "date": "19-11-24",
        "hfs": "2",
        "afs": "0",
        "hhs": "1",
        "ahs": "0"
      },
      {
        "league": "西丙",
        "home": "維拉魯比",
        "away": "維爾瓦 ",
        "date": "19-11-09",
        "hfs": "2",
        "afs": "2",
        "hhs": "1",
        "ahs": "2"
      }
    ]
  }
]