[
  {
    "角球": {
      "home": "6",
      "away": "2"
    },
    "半場角球": {
      "home": "4",
      "away": "1"
    },
    "黃牌": {
      "home": "3",
      "away": "1"
    },
    "射門": {
      "home": "7",
      "away": "9"
    },
    "射正": {
      "home": "1",
      "away": "7"
    },
    "進攻": {
      "home": "64",
      "away": "59"
    },
    "危險進攻": {
      "home": "35",
      "away": "42"
    },
    "射門不中": {
      "home": "6",
      "away": "2"
    },
    "控球率": {
      "home": "52%",
      "away": "48%"
    },
    "半場控球率": {
      "home": "50%",
      "away": "50%"
    },
    "goal": {
      "3+h": "5%",
      "2+h": "15%",
      "1+h": "30%",
      "0+h": "50%",
      "0+a": "35%",
      "1+a": "25%",
      "2+a": "30%",
      "3+a": "10%"
    },
    "odd": {
      "big": "0.87",
      "point": "3/3.5",
      "smal": "0.83"
    },
    "eventArr": [
      {
        "homeText": "",
        "mins": "39",
        "awayText": "入球"
      },
      {
        "homeText": "",
        "mins": "68",
        "awayText": "烏龍"
      }
    ],
    "court": {
      "h15": "15%",
      "h30": "20%",
      "h45": "15%",
      "h60": "15%",
      "h75": "15%",
      "h90": "20%",
      "a15": "18%",
      "a30": "16%",
      "a45": "12%",
      "a60": "20%",
      "a75": "14%",
      "a90": "16%"
    }
  }
]