[
  {
    "home": "0.88",
    "away": "0.96",
    "point": "半球/一球",
    "time": "11-8 21:19",
    "status": "即"
  },
  {
    "home": "0.92",
    "away": "0.92",
    "point": "半球/一球",
    "time": "11-8 21:11",
    "status": "即"
  },
  {
    "home": "0.94",
    "away": "0.90",
    "point": "半球/一球",
    "time": "11-8 21:02",
    "status": "即"
  },
  {
    "home": "1.01",
    "away": "0.83",
    "point": "半球/一球",
    "time": "11-8 20:58",
    "status": "即"
  },
  {
    "home": "1.03",
    "away": "0.80",
    "point": "半球/一球",
    "time": "11-8 14:03",
    "status": "即"
  },
  {
    "home": "0.98",
    "away": "0.84",
    "point": "半球/一球",
    "time": "11-8 14:00",
    "status": "即"
  },
  {
    "home": "0.95",
    "away": "0.87",
    "point": "半球/一球",
    "time": "11-8 12:56",
    "status": "即"
  },
  {
    "home": "0.90",
    "away": "0.92",
    "point": "半球/一球",
    "time": "11-8 12:51",
    "status": "即"
  },
  {
    "home": "0.84",
    "away": "0.98",
    "point": "半球/一球",
    "time": "11-8 12:49",
    "status": "即"
  },
  {
    "home": "0.79",
    "away": "1.04",
    "point": "半球/一球",
    "time": "11-8 12:01",
    "status": "即"
  }
]