[
  {
    "home": "1.22",
    "away": "0.67",
    "point": "半球/一球",
    "time": "10-25 02:12",
    "status": "即"
  },
  {
    "home": "1.18",
    "away": "0.66",
    "point": "半球/一球",
    "time": "10-25 01:46",
    "status": "即"
  },
  {
    "home": "1.10",
    "away": "0.70",
    "point": "半球/一球",
    "time": "10-25 01:41",
    "status": "即"
  },
  {
    "home": "1.05",
    "away": "0.74",
    "point": "半球/一球",
    "time": "10-25 01:40",
    "status": "即"
  },
  {
    "home": "1.00",
    "away": "0.78",
    "point": "半球/一球",
    "time": "10-25 01:39",
    "status": "即"
  },
  {
    "home": "0.92",
    "away": "0.85",
    "point": "半球/一球",
    "time": "10-24 21:30",
    "status": "即"
  },
  {
    "home": "0.90",
    "away": "0.87",
    "point": "半球/一球",
    "time": "10-24 21:28",
    "status": "即"
  },
  {
    "home": "0.88",
    "away": "0.89",
    "point": "半球/一球",
    "time": "10-24 18:45",
    "status": "即"
  },
  {
    "home": "0.86",
    "away": "0.91",
    "point": "半球/一球",
    "time": "10-24 17:31",
    "status": "即"
  },
  {
    "home": "0.84",
    "away": "0.93",
    "point": "半球/一球",
    "time": "10-24 15:37",
    "status": "即"
  },
  {
    "home": "0.82",
    "away": "0.95",
    "point": "半球/一球",
    "time": "10-24 15:28",
    "status": "即"
  },
  {
    "home": "0.92",
    "away": "0.85",
    "point": "一球",
    "time": "10-22 21:27",
    "status": "即"
  },
  {
    "home": "0.90",
    "away": "0.87",
    "point": "一球",
    "time": "10-22 19:34",
    "status": "即"
  },
  {
    "home": "0.84",
    "away": "0.92",
    "point": "一球",
    "time": "10-22 19:12",
    "status": "即"
  }
]