[
  {
    "home": [
      {
        "league": "欧青U21外",
        "home": "法羅群島",
        "away": "北馬其頓",
        "date": "20-09-08",
        "hfs": "1",
        "afs": "2",
        "hhs": "0",
        "ahs": "1"
      },
      {
        "league": "欧青U21外",
        "home": "法羅群島",
        "away": "以色列U",
        "date": "20-09-02",
        "hfs": "3",
        "afs": "1",
        "hhs": "0",
        "ahs": "1"
      },
      {
        "league": "欧青U21外",
        "home": "法羅群島",
        "away": "哈薩克斯",
        "date": "19-06-06",
        "hfs": "1",
        "afs": "3",
        "hhs": "0",
        "ahs": "1"
      },
      {
        "league": "欧青U21外",
        "home": "法羅群島",
        "away": "立陶宛U",
        "date": "18-10-12",
        "hfs": "2",
        "afs": "2",
        "hhs": "1",
        "ahs": "1"
      },
      {
        "league": "欧青U21外",
        "home": "法羅群島",
        "away": "芬蘭U2",
        "date": "18-06-08",
        "hfs": "1",
        "afs": "3",
        "hhs": "1",
        "ahs": "0"
      },
      {
        "league": "欧青U21外",
        "home": "法羅群島",
        "away": "波蘭U21",
        "date": "17-11-11",
        "hfs": "2",
        "afs": "2",
        "hhs": "0",
        "ahs": "1"
      },
      {
        "league": "欧青U21外",
        "home": "法羅群島",
        "away": "格魯吉亞",
        "date": "17-10-11",
        "hfs": "3",
        "afs": "1",
        "hhs": "3",
        "ahs": "1"
      },
      {
        "league": "欧青U21外",
        "home": "法羅群島",
        "away": "奧地利U",
        "date": "16-10-07",
        "hfs": "0",
        "afs": "1",
        "hhs": "0",
        "ahs": "1"
      },
      {
        "league": "欧青U21外",
        "home": "法羅群島",
        "away": "俄羅斯U",
        "date": "16-09-02",
        "hfs": "0",
        "afs": "3",
        "hhs": "0",
        "ahs": "3"
      },
      {
        "league": "欧青U21外",
        "home": "法羅群島",
        "away": "芬蘭U2",
        "date": "16-06-03",
        "hfs": "1",
        "afs": "6",
        "hhs": "1",
        "ahs": "4"
      }
    ],
    "away": [
      {
        "league": "欧青U21外",
        "home": "北馬其頓",
        "away": "西班牙U",
        "date": "20-09-04",
        "hfs": "0",
        "afs": "1",
        "hhs": "0",
        "ahs": "0"
      },
      {
        "league": "欧青U21外",
        "home": "以色列U",
        "away": "西班牙U",
        "date": "19-11-20",
        "hfs": "1",
        "afs": "1",
        "hhs": "0",
        "ahs": "0"
      },
      {
        "league": "欧青U21外",
        "home": "黑山U2",
        "away": "西班牙U",
        "date": "19-10-16",
        "hfs": "0",
        "afs": "2",
        "hhs": "0",
        "ahs": "1"
      },
      {
        "league": "欧青U21外",
        "home": "1哈薩克斯",
        "away": "西班牙U",
        "date": "19-09-06",
        "hfs": "0",
        "afs": "1",
        "hhs": "0",
        "ahs": "1"
      },
      {
        "league": "歐青U21",
        "home": "意大利U",
        "away": "西班牙U",
        "date": "19-06-17",
        "hfs": "3",
        "afs": "1",
        "hhs": "1",
        "ahs": "1"
      },
      {
        "league": "國際友誼",
        "home": "法國U2",
        "away": "西班牙U",
        "date": "18-11-20",
        "hfs": "1",
        "afs": "1",
        "hhs": "0",
        "ahs": "1"
      },
      {
        "league": "欧青U21外",
        "home": "冰島U2",
        "away": "西班牙U",
        "date": "18-10-17",
        "hfs": "2",
        "afs": "7",
        "hhs": "1",
        "ahs": "4"
      },
      {
        "league": "欧青U21外",
        "home": "阿爾巴尼",
        "away": "西班牙U",
        "date": "18-10-12",
        "hfs": "0",
        "afs": "1",
        "hhs": "0",
        "ahs": "0"
      },
      {
        "league": "欧青U21外",
        "home": "北愛爾蘭",
        "away": "西班牙U",
        "date": "18-03-23",
        "hfs": "3",
        "afs": "5",
        "hhs": "2",
        "ahs": "2"
      },
      {
        "league": "欧青U21外",
        "home": "斯洛伐克",
        "away": "西班牙U",
        "date": "17-10-11",
        "hfs": "1",
        "afs": "4",
        "hhs": "0",
        "ahs": "1"
      }
    ]
  }
]