[
  {
    "home": [
      {
        "league": "墨西聯",
        "home": "萊昂  ",
        "away": "祖亞雷斯1",
        "date": "19-09-15",
        "hfs": "3",
        "afs": "1",
        "hhs": "0",
        "ahs": "1"
      },
      {
        "league": "墨西聯",
        "home": "萊昂  ",
        "away": "拿根亞 ",
        "date": "19-08-29",
        "hfs": "2",
        "afs": "2",
        "hhs": "1",
        "ahs": "1"
      },
      {
        "league": "墨西聯",
        "home": "萊昂  ",
        "away": "哥達拿查",
        "date": "19-08-18",
        "hfs": "4",
        "afs": "3",
        "hhs": "2",
        "ahs": "1"
      },
      {
        "league": "墨西聯",
        "home": "1萊昂  ",
        "away": "阿美利加",
        "date": "19-07-28",
        "hfs": "0",
        "afs": "0",
        "hhs": "0",
        "ahs": "0"
      },
      {
        "league": "球會友誼",
        "home": "萊昂  ",
        "away": "紮卡特卡",
        "date": "19-07-03",
        "hfs": "1",
        "afs": "1",
        "hhs": "1",
        "ahs": "1"
      },
      {
        "league": "球會友誼",
        "home": "萊昂  ",
        "away": "祖亞雷斯",
        "date": "19-06-29",
        "hfs": "2",
        "afs": "2",
        "hhs": "2",
        "ahs": "0"
      },
      {
        "league": "墨西聯",
        "home": "1萊昂  ",
        "away": "堤格雷斯",
        "date": "19-05-27",
        "hfs": "0",
        "afs": "0",
        "hhs": "0",
        "ahs": "0"
      },
      {
        "league": "墨西聯",
        "home": "1萊昂  ",
        "away": "阿美利加1",
        "date": "19-05-20",
        "hfs": "0",
        "afs": "1",
        "hhs": "0",
        "ahs": "1"
      },
      {
        "league": "墨西聯",
        "home": "萊昂  ",
        "away": "堤華納 ",
        "date": "19-05-12",
        "hfs": "2",
        "afs": "1",
        "hhs": "2",
        "ahs": "1"
      },
      {
        "league": "墨西聯",
        "home": "萊昂  ",
        "away": "帕丘卡 ",
        "date": "19-05-05",
        "hfs": "2",
        "afs": "1",
        "hhs": "1",
        "ahs": "0"
      }
    ],
    "away": [
      {
        "league": "墨西聯",
        "home": "哥達拿查",
        "away": "阿特拿斯1",
        "date": "19-09-15",
        "hfs": "1",
        "afs": "0",
        "hhs": "0",
        "ahs": "0"
      },
      {
        "league": "球會友誼",
        "home": "底特律城",
        "away": "阿特拿斯",
        "date": "19-09-08",
        "hfs": "2",
        "afs": "1",
        "hhs": "1",
        "ahs": "1"
      },
      {
        "league": "墨西聯",
        "home": "帕丘卡 ",
        "away": "阿特拿斯",
        "date": "19-08-25",
        "hfs": "3",
        "afs": "1",
        "hhs": "2",
        "ahs": "0"
      },
      {
        "league": "墨西聯",
        "home": "華拿古斯",
        "away": "阿特拿斯",
        "date": "19-08-10",
        "hfs": "1",
        "afs": "2",
        "hhs": "1",
        "ahs": "0"
      },
      {
        "league": "墨西哥盃",
        "home": "薩卡特佩",
        "away": "阿特拿斯",
        "date": "19-08-07",
        "hfs": "3",
        "afs": "2",
        "hhs": "0",
        "ahs": "1"
      },
      {
        "league": "墨西聯",
        "home": "莫雷利亞",
        "away": "阿特拿斯",
        "date": "19-07-27",
        "hfs": "0",
        "afs": "1",
        "hhs": "0",
        "ahs": "0"
      },
      {
        "league": "球會友誼",
        "home": "尼卡沙 ",
        "away": "阿特拿斯",
        "date": "19-07-04",
        "hfs": "1",
        "afs": "1",
        "hhs": "0",
        "ahs": "1"
      },
      {
        "league": "墨西聯",
        "home": "帕丘卡 ",
        "away": "阿特拿斯2",
        "date": "19-04-28",
        "hfs": "1",
        "afs": "0",
        "hhs": "0",
        "ahs": "0"
      },
      {
        "league": "墨西聯",
        "home": "萊昂  ",
        "away": "阿特拿斯",
        "date": "19-04-21",
        "hfs": "5",
        "afs": "2",
        "hhs": "1",
        "ahs": "0"
      },
      {
        "league": "墨西聯",
        "home": "華拿古斯",
        "away": "阿特拿斯",
        "date": "19-04-06",
        "hfs": "0",
        "afs": "1",
        "hhs": "0",
        "ahs": "0"
      }
    ]
  }
]