[
  {
    "home": [
      {
        "league": "葡超",
        "home": "博維斯塔",
        "away": "樸迪莫倫",
        "date": "20-01-04",
        "hfs": "1",
        "afs": "1",
        "hhs": "0",
        "ahs": "0"
      },
      {
        "league": "葡超",
        "home": "博維斯塔",
        "away": "賓菲加 ",
        "date": "19-12-07",
        "hfs": "1",
        "afs": "4",
        "hhs": "1",
        "ahs": "1"
      },
      {
        "league": "葡超",
        "home": "博維斯塔",
        "away": "波圖  ",
        "date": "19-11-11",
        "hfs": "0",
        "afs": "1",
        "hhs": "0",
        "ahs": "1"
      },
      {
        "league": "葡超",
        "home": "博維斯塔",
        "away": "布拉加 ",
        "date": "19-11-01",
        "hfs": "2",
        "afs": "0",
        "hhs": "1",
        "ahs": "0"
      },
      {
        "league": "葡超",
        "home": "博維斯塔",
        "away": "唐迪拉 ",
        "date": "19-09-28",
        "hfs": "0",
        "afs": "0",
        "hhs": "0",
        "ahs": "0"
      },
      {
        "league": "葡超",
        "home": "博維斯塔",
        "away": "士砵亭 1",
        "date": "19-09-16",
        "hfs": "1",
        "afs": "1",
        "hhs": "1",
        "ahs": "0"
      },
      {
        "league": "葡超",
        "home": "博維斯塔",
        "away": "費利拿 ",
        "date": "19-08-25",
        "hfs": "1",
        "afs": "1",
        "hhs": "1",
        "ahs": "1"
      },
      {
        "league": "葡超",
        "home": "博維斯塔",
        "away": "艾維斯 ",
        "date": "19-08-11",
        "hfs": "2",
        "afs": "1",
        "hhs": "1",
        "ahs": "1"
      },
      {
        "league": "球會友誼",
        "home": "博維斯塔",
        "away": "奈斯  ",
        "date": "19-07-25",
        "hfs": "0",
        "afs": "2",
        "hhs": "0",
        "ahs": "2"
      },
      {
        "league": "葡超",
        "home": "博維斯塔",
        "away": "布拉加 ",
        "date": "19-05-12",
        "hfs": "4",
        "afs": "2",
        "hhs": "3",
        "ahs": "2"
      }
    ],
    "away": [
      {
        "league": "葡超",
        "home": "賓菲加 ",
        "away": "法馬利卡",
        "date": "19-12-15",
        "hfs": "4",
        "afs": "0",
        "hhs": "1",
        "ahs": "0"
      },
      {
        "league": "葡超",
        "home": "樸迪莫倫",
        "away": "法馬利卡",
        "date": "19-12-01",
        "hfs": "2",
        "afs": "1",
        "hhs": "1",
        "ahs": "0"
      },
      {
        "league": "葡超",
        "home": "布拉加 ",
        "away": "法馬利卡1",
        "date": "19-11-04",
        "hfs": "2",
        "afs": "2",
        "hhs": "0",
        "ahs": "0"
      },
      {
        "league": "葡超",
        "home": "波圖  ",
        "away": "法馬利卡",
        "date": "19-10-28",
        "hfs": "3",
        "afs": "0",
        "hhs": "1",
        "ahs": "0"
      },
      {
        "league": "葡盃",
        "home": "1路斯坦尼",
        "away": "法馬利卡",
        "date": "19-10-20",
        "hfs": "1",
        "afs": "1",
        "hhs": "0",
        "ahs": "0"
      },
      {
        "league": "葡超",
        "home": "士砵亭 ",
        "away": "法馬利卡",
        "date": "19-09-24",
        "hfs": "1",
        "afs": "2",
        "hhs": "1",
        "ahs": "0"
      },
      {
        "league": "球會友誼",
        "home": "切爾達 ",
        "away": "法馬利卡",
        "date": "19-09-06",
        "hfs": "1",
        "afs": "1",
        "hhs": "0",
        "ahs": "0"
      },
      {
        "league": "葡超",
        "home": "1艾維斯 ",
        "away": "法馬利卡1",
        "date": "19-08-31",
        "hfs": "2",
        "afs": "3",
        "hhs": "1",
        "ahs": "1"
      },
      {
        "league": "葡超",
        "home": "甘馬雷斯",
        "away": "法馬利卡",
        "date": "19-08-26",
        "hfs": "1",
        "afs": "1",
        "hhs": "0",
        "ahs": "0"
      },
      {
        "league": "葡超",
        "home": "辛達卡拉",
        "away": "法馬利卡",
        "date": "19-08-10",
        "hfs": "0",
        "afs": "2",
        "hhs": "0",
        "ahs": "1"
      }
    ]
  }
]