[
  {
    "home": [
      {
        "league": "西甲",
        "home": "西維爾 ",
        "away": "貝迪斯 ",
        "date": "20-06-12",
        "hfs": "2",
        "afs": "0",
        "hhs": "0",
        "ahs": "0"
      },
      {
        "league": "西甲",
        "home": "西維爾 ",
        "away": "奧沙辛拿1",
        "date": "20-03-01",
        "hfs": "3",
        "afs": "2",
        "hhs": "2",
        "ahs": "0"
      },
      {
        "league": "歐霸盃",
        "home": "西維爾 ",
        "away": "克盧日 1",
        "date": "20-02-28",
        "hfs": "0",
        "afs": "0",
        "hhs": "0",
        "ahs": "0"
      },
      {
        "league": "西甲",
        "home": "西維爾 ",
        "away": "愛斯賓奴1",
        "date": "20-02-16",
        "hfs": "2",
        "afs": "2",
        "hhs": "1",
        "ahs": "1"
      },
      {
        "league": "西甲",
        "home": "西維爾 ",
        "away": "艾拉維斯",
        "date": "20-02-03",
        "hfs": "1",
        "afs": "1",
        "hhs": "0",
        "ahs": "0"
      },
      {
        "league": "西甲",
        "home": "西維爾 ",
        "away": "格蘭納達",
        "date": "20-01-26",
        "hfs": "2",
        "afs": "0",
        "hhs": "2",
        "ahs": "0"
      },
      {
        "league": "西盃",
        "home": "西維爾 ",
        "away": "利雲特 ",
        "date": "20-01-22",
        "hfs": "3",
        "afs": "1",
        "hhs": "1",
        "ahs": "1"
      },
      {
        "league": "西甲",
        "home": "西維爾 ",
        "away": "畢爾包 ",
        "date": "20-01-04",
        "hfs": "1",
        "afs": "1",
        "hhs": "0",
        "ahs": "1"
      },
      {
        "league": "西甲",
        "home": "西維爾 ",
        "away": "維拉利爾",
        "date": "19-12-16",
        "hfs": "1",
        "afs": "2",
        "hhs": "0",
        "ahs": "1"
      },
      {
        "league": "西甲",
        "home": "西維爾 ",
        "away": "雷加利斯",
        "date": "19-12-01",
        "hfs": "1",
        "afs": "0",
        "hhs": "0",
        "ahs": "0"
      }
    ],
    "away": [
      {
        "league": "西甲",
        "home": "馬略卡 ",
        "away": "巴塞隆拿",
        "date": "20-06-14",
        "hfs": "0",
        "afs": "4",
        "hhs": "0",
        "ahs": "2"
      },
      {
        "league": "西甲",
        "home": "皇家馬德",
        "away": "巴塞隆拿",
        "date": "20-03-02",
        "hfs": "2",
        "afs": "0",
        "hhs": "0",
        "ahs": "0"
      },
      {
        "league": "歐冠盃",
        "home": "拿玻里 ",
        "away": "巴塞隆拿1",
        "date": "20-02-26",
        "hfs": "1",
        "afs": "1",
        "hhs": "1",
        "ahs": "0"
      },
      {
        "league": "西甲",
        "home": "1貝迪斯 ",
        "away": "巴塞隆拿1",
        "date": "20-02-10",
        "hfs": "2",
        "afs": "3",
        "hhs": "2",
        "ahs": "2"
      },
      {
        "league": "西盃",
        "home": "畢爾包 ",
        "away": "巴塞隆拿",
        "date": "20-02-07",
        "hfs": "1",
        "afs": "0",
        "hhs": "0",
        "ahs": "0"
      },
      {
        "league": "西甲",
        "home": "華倫西亞",
        "away": "巴塞隆拿",
        "date": "20-01-25",
        "hfs": "2",
        "afs": "0",
        "hhs": "0",
        "ahs": "0"
      },
      {
        "league": "西盃",
        "home": "UD伊比",
        "away": "巴塞隆拿",
        "date": "20-01-23",
        "hfs": "1",
        "afs": "2",
        "hhs": "1",
        "ahs": "0"
      },
      {
        "league": "西甲",
        "home": "愛斯賓奴",
        "away": "巴塞隆拿1",
        "date": "20-01-05",
        "hfs": "2",
        "afs": "2",
        "hhs": "1",
        "ahs": "0"
      },
      {
        "league": "西甲",
        "home": "皇家蘇斯",
        "away": "巴塞隆拿",
        "date": "19-12-14",
        "hfs": "2",
        "afs": "2",
        "hhs": "1",
        "ahs": "1"
      },
      {
        "league": "歐冠盃",
        "home": "國際米蘭",
        "away": "巴塞隆拿",
        "date": "19-12-11",
        "hfs": "1",
        "afs": "2",
        "hhs": "1",
        "ahs": "1"
      }
    ]
  }
]