[
  {
    "home": "0.93",
    "away": "0.91",
    "point": "半球/一球",
    "time": "9-27 20:46",
    "status": "即"
  },
  {
    "home": "0.96",
    "away": "0.88",
    "point": "半球/一球",
    "time": "9-27 20:41",
    "status": "即"
  },
  {
    "home": "1.00",
    "away": "0.84",
    "point": "半球/一球",
    "time": "9-27 20:21",
    "status": "即"
  },
  {
    "home": "0.98",
    "away": "0.86",
    "point": "半球/一球",
    "time": "9-27 20:21",
    "status": "即"
  },
  {
    "home": "0.95",
    "away": "0.89",
    "point": "半球/一球",
    "time": "9-27 19:42",
    "status": "即"
  },
  {
    "home": "0.97",
    "away": "0.87",
    "point": "半球/一球",
    "time": "9-27 19:23",
    "status": "即"
  },
  {
    "home": "1.00",
    "away": "0.84",
    "point": "半球/一球",
    "time": "9-27 16:58",
    "status": "即"
  },
  {
    "home": "1.03",
    "away": "0.81",
    "point": "半球/一球",
    "time": "9-27 16:38",
    "status": "即"
  },
  {
    "home": "1.07",
    "away": "0.78",
    "point": "半球/一球",
    "time": "9-27 16:20",
    "status": "即"
  },
  {
    "home": "1.05",
    "away": "0.74",
    "point": "半球/一球",
    "time": "9-27 03:38",
    "status": "即"
  },
  {
    "home": "1.00",
    "away": "0.78",
    "point": "半球/一球",
    "time": "9-26 19:17",
    "status": "即"
  }
]