[
  {
    "home": [
      {
        "league": "哥倫乙",
        "home": "卡達根拿",
        "away": "皇家桑坦",
        "date": "20-10-08",
        "hfs": "2",
        "afs": "3",
        "hhs": "1",
        "ahs": "2"
      },
      {
        "league": "哥倫乙",
        "home": "卡達根拿",
        "away": "錫帕基拉",
        "date": "20-10-05",
        "hfs": "0",
        "afs": "0",
        "hhs": "0",
        "ahs": "0"
      },
      {
        "league": "哥倫盃",
        "home": "卡達根拿",
        "away": "錫帕基拉1",
        "date": "20-09-24",
        "hfs": "0",
        "afs": "0",
        "hhs": "0",
        "ahs": "0"
      },
      {
        "league": "哥倫乙",
        "home": "卡達根拿",
        "away": "奧爾索馬1",
        "date": "20-09-20",
        "hfs": "0",
        "afs": "1",
        "hhs": "0",
        "ahs": "0"
      },
      {
        "league": "哥倫乙",
        "home": "卡達根拿",
        "away": "馬達萊納",
        "date": "20-03-09",
        "hfs": "0",
        "afs": "2",
        "hhs": "0",
        "ahs": "1"
      },
      {
        "league": "哥倫盃",
        "home": "1卡達根拿",
        "away": "卡利競技",
        "date": "20-03-05",
        "hfs": "1",
        "afs": "1",
        "hhs": "0",
        "ahs": "1"
      },
      {
        "league": "哥倫乙",
        "home": "卡達根拿",
        "away": "瓦倫杜帕",
        "date": "20-02-24",
        "hfs": "0",
        "afs": "1",
        "hhs": "0",
        "ahs": "1"
      },
      {
        "league": "哥倫乙",
        "home": "卡達根拿",
        "away": "卡利競技",
        "date": "20-02-10",
        "hfs": "2",
        "afs": "1",
        "hhs": "1",
        "ahs": "0"
      },
      {
        "league": "哥倫乙",
        "home": "卡達根拿",
        "away": "波哥塔 ",
        "date": "19-11-18",
        "hfs": "1",
        "afs": "0",
        "hhs": "1",
        "ahs": "0"
      },
      {
        "league": "哥倫乙",
        "home": "卡達根拿",
        "away": "福塔雷紹",
        "date": "19-11-10",
        "hfs": "2",
        "afs": "2",
        "hhs": "1",
        "ahs": "0"
      }
    ],
    "away": [
      {
        "league": "哥倫乙",
        "home": "2奧爾索馬",
        "away": "福塔雷紹1",
        "date": "20-10-09",
        "hfs": "3",
        "afs": "2",
        "hhs": "1",
        "ahs": "0"
      },
      {
        "league": "哥倫盃",
        "home": "奎迪奧 ",
        "away": "福塔雷紹",
        "date": "20-10-02",
        "hfs": "1",
        "afs": "0",
        "hhs": "0",
        "ahs": "0"
      },
      {
        "league": "哥倫乙",
        "home": "馬達萊納",
        "away": "福塔雷紹",
        "date": "20-09-29",
        "hfs": "2",
        "afs": "1",
        "hhs": "1",
        "ahs": "0"
      },
      {
        "league": "哥倫乙",
        "home": "瓦倫杜帕",
        "away": "福塔雷紹",
        "date": "20-03-13",
        "hfs": "0",
        "afs": "1",
        "hhs": "0",
        "ahs": "1"
      },
      {
        "league": "哥倫乙",
        "home": "卡利競技",
        "away": "福塔雷紹",
        "date": "20-02-28",
        "hfs": "0",
        "afs": "0",
        "hhs": "0",
        "ahs": "0"
      },
      {
        "league": "哥倫盃",
        "home": "奧爾索馬",
        "away": "福塔雷紹",
        "date": "20-02-21",
        "hfs": "1",
        "afs": "2",
        "hhs": "1",
        "ahs": "1"
      },
      {
        "league": "哥倫乙",
        "home": "1希拿體育",
        "away": "福塔雷紹",
        "date": "20-02-18",
        "hfs": "1",
        "afs": "1",
        "hhs": "1",
        "ahs": "0"
      },
      {
        "league": "哥倫乙",
        "home": "錫帕基拉",
        "away": "福塔雷紹",
        "date": "20-02-02",
        "hfs": "1",
        "afs": "2",
        "hhs": "1",
        "ahs": "1"
      },
      {
        "league": "哥倫乙",
        "home": "波哥塔 ",
        "away": "福塔雷紹1",
        "date": "19-11-13",
        "hfs": "0",
        "afs": "3",
        "hhs": "0",
        "ahs": "0"
      },
      {
        "league": "哥倫乙",
        "home": "卡達根拿",
        "away": "福塔雷紹",
        "date": "19-11-10",
        "hfs": "2",
        "afs": "2",
        "hhs": "1",
        "ahs": "0"
      }
    ]
  }
]