[
  {
    "home": "0.86",
    "away": "0.98",
    "point": "半球/一球",
    "time": "1-12 22:58",
    "status": "即"
  },
  {
    "home": "0.89",
    "away": "0.95",
    "point": "半球/一球",
    "time": "1-12 22:50",
    "status": "即"
  },
  {
    "home": "0.91",
    "away": "0.93",
    "point": "半球/一球",
    "time": "1-12 22:46",
    "status": "即"
  },
  {
    "home": "0.93",
    "away": "0.91",
    "point": "半球/一球",
    "time": "1-12 22:08",
    "status": "即"
  },
  {
    "home": "0.95",
    "away": "0.89",
    "point": "半球/一球",
    "time": "1-12 22:05",
    "status": "即"
  },
  {
    "home": "0.97",
    "away": "0.87",
    "point": "半球/一球",
    "time": "1-12 22:04",
    "status": "即"
  },
  {
    "home": "1.02",
    "away": "0.82",
    "point": "半球/一球",
    "time": "1-12 22:02",
    "status": "即"
  },
  {
    "home": "1.10",
    "away": "0.76",
    "point": "半球/一球",
    "time": "1-9 19:23",
    "status": "即"
  }
]