[
  {
    "home": "0.94",
    "away": "0.88",
    "point": "平手/半球",
    "time": "10-6 01:38",
    "status": "即"
  },
  {
    "home": "0.91",
    "away": "0.90",
    "point": "平手/半球",
    "time": "10-6 01:35",
    "status": "即"
  },
  {
    "home": "0.89",
    "away": "0.92",
    "point": "平手/半球",
    "time": "10-6 01:29",
    "status": "即"
  },
  {
    "home": "0.86",
    "away": "0.96",
    "point": "平手/半球",
    "time": "10-5 20:00",
    "status": "即"
  },
  {
    "home": "0.83",
    "away": "0.99",
    "point": "平手/半球",
    "time": "10-5 19:36",
    "status": "即"
  },
  {
    "home": "0.81",
    "away": "1.02",
    "point": "平手/半球",
    "time": "10-5 09:44",
    "status": "即"
  }
]