[
  {
    "home": "82",
    "away": "封",
    "point": "1-0",
    "time": "9-9 01:45",
    "status": "滚"
  },
  {
    "home": "75",
    "away": "1.15",
    "point": "1-0",
    "time": "平手",
    "status": "0.50"
  },
  {
    "home": "70",
    "away": "1.10",
    "point": "1-0",
    "time": "平手",
    "status": "0.55"
  },
  {
    "home": "66",
    "away": "1.00",
    "point": "1-0",
    "time": "平手",
    "status": "0.65"
  },
  {
    "home": "66",
    "away": "1.05",
    "point": "1-0",
    "time": "平手",
    "status": "0.60"
  },
  {
    "home": "60",
    "away": "1.05",
    "point": "0-0",
    "time": "一球",
    "status": "0.60"
  },
  {
    "home": "55",
    "away": "1.00",
    "point": "0-0",
    "time": "平手",
    "status": "0.65"
  },
  {
    "home": "51",
    "away": "0.65",
    "point": "0-0",
    "time": "受让平手/半球",
    "status": "1.00"
  },
  {
    "home": "51",
    "away": "0.70",
    "point": "0-0",
    "time": "受让平手/半球",
    "status": "0.95"
  },
  {
    "home": "46",
    "away": "0.80",
    "point": "0-0",
    "time": "受让平手/半球",
    "status": "0.85"
  },
  {
    "home": "45",
    "away": "0.90",
    "point": "0-0",
    "time": "受让平手/半球",
    "status": "0.75"
  },
  {
    "home": "42",
    "away": "0.70",
    "point": "0-0",
    "time": "受让半球",
    "status": "0.95"
  },
  {
    "home": "40",
    "away": "0.75",
    "point": "0-0",
    "time": "受让半球",
    "status": "0.90"
  },
  {
    "home": "16",
    "away": "0.80",
    "point": "0-0",
    "time": "受让半球",
    "status": "0.85"
  },
  {
    "home": "11",
    "away": "0.95",
    "point": "0-0",
    "time": "受让平手/半球",
    "status": "0.70"
  },
  {
    "home": "01",
    "away": "0.90",
    "point": "0-0",
    "time": "受让平手/半球",
    "status": "0.75"
  },
  {
    "home": "0.86",
    "away": "0.84",
    "point": "受让平手/半球",
    "time": "9-8 23:12",
    "status": "即"
  },
  {
    "home": "0.90",
    "away": "0.80",
    "point": "受让平手/半球",
    "time": "9-8 17:44",
    "status": "即"
  },
  {
    "home": "0.87",
    "away": "0.83",
    "point": "受让平手/半球",
    "time": "9-8 17:01",
    "status": "即"
  }
]